phip/__init__.py
phip/cli.py
phip/clipped_factorization.py
phip/gampois.py
phip/genpois.py
phip/hit_calling.py
phip/utils.py
phip_stat-0.5.1.dist-info/LICENSE.txt
phip_stat-0.5.1.dist-info/METADATA
phip_stat-0.5.1.dist-info/WHEEL
phip_stat-0.5.1.dist-info/entry_points.txt
phip_stat-0.5.1.dist-info/top_level.txt
phip_stat-0.5.1.dist-info/RECORD
