Metadata-Version: 2.1
Name: phip-stat
Version: 0.5.1
Summary: PhIP-seq analysis tools
Home-page: https://github.com/lasersonlab/phip-stat
Author: Laserson Lab
License: Apache License, Version 2.0
Platform: UNKNOWN
Classifier: Programming Language :: Python :: 2.6
Classifier: Programming Language :: Python :: 2.7
Classifier: Programming Language :: Python :: 3
License-File: LICENSE.txt
Requires-Dist: click
Requires-Dist: tqdm
Requires-Dist: numpy
Requires-Dist: scipy
Requires-Dist: pandas
